ezqueue.py
ezqueue-0.2.2.dist-info/LICENSE
ezqueue-0.2.2.dist-info/WHEEL
ezqueue-0.2.2.dist-info/METADATA
ezqueue-0.2.2.dist-info/RECORD
