Metadata-Version: 2.1
Name: ezqueue
Version: 0.2.2
Summary: Easy queue allows for fixed size array and unique keys
Home-page: https://github.com/jwcnewton/ezqueue
License: MIT
Author: jwcnewton
Requires-Python: >=3.7,<4.0
Classifier: License :: OSI Approved :: MIT License
Classifier: Programming Language :: Python :: 3
Classifier: Programming Language :: Python :: 3.7
Classifier: Programming Language :: Python :: 3.8
Classifier: Programming Language :: Python :: 3.9
Project-URL: Documentation, https://ezqueue.readthedocs.io/en/latest/
Project-URL: Repository, https://github.com/jwcnewton/ezqueue
